[
  {
    "timestamp": "2025-09-13T04:41:20.657Z"
  },
  {
    "timestamp": "2025-09-13T04:53:10.115Z"
  },
  {
    "timestamp": "2025-09-13T05:19:09.109Z"
  },
  {
    "timestamp": "2025-09-13T05:39:19.239Z"
  },
  {
    "timestamp": "2025-09-13T05:52:03.229Z"
  },
  {
    "timestamp": "2025-09-13T06:28:27.926Z"
  },
  {
    "timestamp": "2025-09-13T06:45:32.185Z"
  },
  {
    "timestamp": "2025-09-13T07:17:34.085Z"
  },
  {
    "timestamp": "2025-09-13T07:38:03.358Z"
  },
  {
    "timestamp": "2025-09-13T07:52:12.593Z"
  },
  {
    "timestamp": "2025-09-13T08:24:42.206Z"
  },
  {
    "timestamp": "2025-09-13T08:41:57.902Z"
  },
  {
    "timestamp": "2025-09-13T08:54:03.054Z"
  },
  {
    "timestamp": "2025-09-13T09:18:52.501Z"
  },
  {
    "timestamp": "2025-09-13T09:38:07.891Z"
  },
  {
    "timestamp": "2025-09-13T09:52:22.569Z"
  },
  {
    "timestamp": "2025-09-13T10:19:28.972Z"
  },
  {
    "timestamp": "2025-09-13T10:39:02.124Z"
  },
  {
    "timestamp": "2025-09-13T10:51:57.392Z"
  },
  {
    "timestamp": "2025-09-13T11:15:19.767Z"
  },
  {
    "timestamp": "2025-09-13T11:26:52.261Z"
  },
  {
    "timestamp": "2025-09-13T11:39:36.667Z"
  },
  {
    "timestamp": "2025-09-13T11:52:18.604Z"
  },
  {
    "timestamp": "2025-09-13T12:38:46.028Z"
  },
  {
    "timestamp": "2025-09-13T13:02:45.830Z"
  },
  {
    "timestamp": "2025-09-13T13:29:33.915Z"
  },
  {
    "timestamp": "2025-09-13T13:41:23.033Z"
  },
  {
    "timestamp": "2025-09-13T13:53:24.837Z"
  },
  {
    "timestamp": "2025-09-13T14:16:11.806Z"
  },
  {
    "timestamp": "2025-09-13T14:37:16.601Z"
  },
  {
    "timestamp": "2025-09-13T14:52:12.016Z"
  },
  {
    "timestamp": "2025-09-13T15:18:03.250Z"
  },
  {
    "timestamp": "2025-09-13T15:38:05.150Z"
  },
  {
    "timestamp": "2025-09-13T15:52:27.829Z"
  },
  {
    "timestamp": "2025-09-13T16:22:29.746Z"
  },
  {
    "timestamp": "2025-09-13T16:40:56.812Z"
  },
  {
    "timestamp": "2025-09-13T16:52:37.464Z"
  },
  {
    "timestamp": "2025-09-13T17:15:22.000Z"
  },
  {
    "timestamp": "2025-09-13T17:28:22.703Z"
  },
  {
    "timestamp": "2025-09-13T17:39:54.494Z"
  },
  {
    "timestamp": "2025-09-13T17:52:17.742Z"
  },
  {
    "timestamp": "2025-09-13T18:26:10.703Z"
  },
  {
    "timestamp": "2025-09-13T18:42:33.951Z"
  },
  {
    "timestamp": "2025-09-13T18:54:22.796Z"
  },
  {
    "timestamp": "2025-09-13T19:14:55.645Z"
  },
  {
    "timestamp": "2025-09-13T19:26:43.721Z"
  },
  {
    "timestamp": "2025-09-13T19:38:41.765Z"
  },
  {
    "timestamp": "2025-09-13T19:52:21.847Z"
  },
  {
    "timestamp": "2025-09-13T20:19:59.004Z"
  },
  {
    "timestamp": "2025-09-13T20:38:18.494Z"
  },
  {
    "timestamp": "2025-09-13T20:52:35.639Z"
  },
  {
    "timestamp": "2025-09-13T21:16:55.894Z"
  },
  {
    "timestamp": "2025-09-13T21:38:04.110Z"
  },
  {
    "timestamp": "2025-09-13T21:52:06.708Z"
  },
  {
    "timestamp": "2025-09-13T22:17:49.293Z"
  },
  {
    "timestamp": "2025-09-13T22:38:24.178Z"
  },
  {
    "timestamp": "2025-09-13T22:52:27.630Z"
  },
  {
    "timestamp": "2025-09-13T23:17:44.902Z"
  },
  {
    "timestamp": "2025-09-13T23:38:49.074Z"
  },
  {
    "timestamp": "2025-09-13T23:52:11.168Z"
  },
  {
    "timestamp": "2025-09-14T01:47:12.912Z"
  },
  {
    "timestamp": "2025-09-14T03:03:57.186Z"
  },
  {
    "timestamp": "2025-09-14T03:42:17.532Z"
  },
  {
    "timestamp": "2025-09-14T03:53:54.238Z"
  },
  {
    "timestamp": "2025-09-14T04:24:35.897Z"
  },
  {
    "timestamp": "2025-09-14T04:41:29.913Z"
  },
  {
    "timestamp": "2025-09-14T04:53:14.864Z"
  },
  {
    "timestamp": "2025-09-14T05:19:15.812Z"
  },
  {
    "timestamp": "2025-09-14T05:39:13.989Z"
  },
  {
    "timestamp": "2025-09-14T05:52:15.546Z"
  },
  {
    "timestamp": "2025-09-14T06:29:19.048Z"
  },
  {
    "timestamp": "2025-09-14T06:47:05.690Z"
  },
  {
    "timestamp": "2025-09-14T07:18:19.685Z"
  },
  {
    "timestamp": "2025-09-14T07:38:18.218Z"
  },
  {
    "timestamp": "2025-09-14T07:52:00.794Z"
  },
  {
    "timestamp": "2025-09-14T08:25:32.549Z"
  },
  {
    "timestamp": "2025-09-14T08:42:03.177Z"
  },
  {
    "timestamp": "2025-09-14T08:53:29.031Z"
  },
  {
    "timestamp": "2025-09-14T09:19:05.191Z"
  },
  {
    "timestamp": "2025-09-14T09:38:40.907Z"
  },
  {
    "timestamp": "2025-09-14T09:52:18.182Z"
  },
  {
    "timestamp": "2025-09-14T10:18:51.046Z"
  },
  {
    "timestamp": "2025-09-14T10:38:22.038Z"
  },
  {
    "timestamp": "2025-09-14T10:52:30.304Z"
  },
  {
    "timestamp": "2025-09-14T11:15:03.858Z"
  },
  {
    "timestamp": "2025-09-14T11:26:57.071Z"
  },
  {
    "timestamp": "2025-09-14T11:39:11.350Z"
  },
  {
    "timestamp": "2025-09-14T11:52:18.542Z"
  },
  {
    "timestamp": "2025-09-14T12:38:22.699Z"
  },
  {
    "timestamp": "2025-09-14T13:02:13.869Z"
  },
  {
    "timestamp": "2025-09-14T13:28:58.346Z"
  },
  {
    "timestamp": "2025-09-14T13:40:52.083Z"
  },
  {
    "timestamp": "2025-09-14T13:52:44.338Z"
  },
  {
    "timestamp": "2025-09-14T14:17:06.913Z"
  },
  {
    "timestamp": "2025-09-14T14:37:58.189Z"
  },
  {
    "timestamp": "2025-09-14T14:52:23.493Z"
  },
  {
    "timestamp": "2025-09-14T15:18:36.786Z"
  },
  {
    "timestamp": "2025-09-14T15:37:53.715Z"
  },
  {
    "timestamp": "2025-09-14T15:52:16.436Z"
  },
  {
    "timestamp": "2025-09-14T16:22:29.119Z"
  }
]