[
  {
    "timestamp": "2025-08-29T10:43:03.036Z"
  },
  {
    "timestamp": "2025-08-29T10:54:55.053Z"
  },
  {
    "timestamp": "2025-08-29T11:17:54.853Z"
  },
  {
    "timestamp": "2025-08-29T11:39:08.817Z"
  },
  {
    "timestamp": "2025-08-29T11:52:16.973Z"
  },
  {
    "timestamp": "2025-08-29T12:44:25.430Z"
  },
  {
    "timestamp": "2025-08-29T13:16:55.300Z"
  },
  {
    "timestamp": "2025-08-29T13:43:42.292Z"
  },
  {
    "timestamp": "2025-08-29T13:55:28.385Z"
  },
  {
    "timestamp": "2025-08-29T14:20:26.435Z"
  },
  {
    "timestamp": "2025-08-29T14:42:46.501Z"
  },
  {
    "timestamp": "2025-08-29T14:54:31.538Z"
  },
  {
    "timestamp": "2025-08-29T15:19:55.859Z"
  },
  {
    "timestamp": "2025-08-29T15:40:18.051Z"
  },
  {
    "timestamp": "2025-08-29T15:52:28.227Z"
  },
  {
    "timestamp": "2025-08-29T16:27:03.504Z"
  },
  {
    "timestamp": "2025-08-29T16:47:40.219Z"
  },
  {
    "timestamp": "2025-08-29T17:18:44.271Z"
  },
  {
    "timestamp": "2025-08-29T17:40:27.496Z"
  },
  {
    "timestamp": "2025-08-29T17:52:17.195Z"
  },
  {
    "timestamp": "2025-08-29T18:28:13.562Z"
  },
  {
    "timestamp": "2025-08-29T18:47:30.698Z"
  },
  {
    "timestamp": "2025-08-29T19:16:30.774Z"
  },
  {
    "timestamp": "2025-08-29T19:38:38.437Z"
  },
  {
    "timestamp": "2025-08-29T19:52:05.746Z"
  },
  {
    "timestamp": "2025-08-29T20:22:58.356Z"
  },
  {
    "timestamp": "2025-08-29T20:40:29.431Z"
  },
  {
    "timestamp": "2025-08-29T20:52:12.128Z"
  },
  {
    "timestamp": "2025-08-29T21:19:07.332Z"
  },
  {
    "timestamp": "2025-08-29T21:38:04.906Z"
  },
  {
    "timestamp": "2025-08-29T21:52:15.023Z"
  },
  {
    "timestamp": "2025-08-29T22:19:44.554Z"
  },
  {
    "timestamp": "2025-08-29T22:40:47.212Z"
  },
  {
    "timestamp": "2025-08-29T22:52:29.531Z"
  },
  {
    "timestamp": "2025-08-29T23:19:48.184Z"
  },
  {
    "timestamp": "2025-08-29T23:38:13.626Z"
  },
  {
    "timestamp": "2025-08-29T23:52:18.725Z"
  },
  {
    "timestamp": "2025-08-30T01:39:52.137Z"
  },
  {
    "timestamp": "2025-08-30T02:46:27.608Z"
  },
  {
    "timestamp": "2025-08-30T03:30:48.167Z"
  },
  {
    "timestamp": "2025-08-30T03:52:34.148Z"
  },
  {
    "timestamp": "2025-08-30T04:24:46.213Z"
  },
  {
    "timestamp": "2025-08-30T04:42:07.032Z"
  },
  {
    "timestamp": "2025-08-30T04:53:36.485Z"
  },
  {
    "timestamp": "2025-08-30T05:19:19.184Z"
  },
  {
    "timestamp": "2025-08-30T05:40:00.103Z"
  },
  {
    "timestamp": "2025-08-30T05:52:17.846Z"
  },
  {
    "timestamp": "2025-08-30T06:28:50.632Z"
  },
  {
    "timestamp": "2025-08-30T06:46:52.744Z"
  },
  {
    "timestamp": "2025-08-30T07:18:07.994Z"
  },
  {
    "timestamp": "2025-08-30T07:38:15.362Z"
  },
  {
    "timestamp": "2025-08-30T07:51:57.411Z"
  },
  {
    "timestamp": "2025-08-30T08:25:39.219Z"
  },
  {
    "timestamp": "2025-08-30T08:43:19.159Z"
  },
  {
    "timestamp": "2025-08-30T08:54:56.949Z"
  },
  {
    "timestamp": "2025-08-30T09:19:46.954Z"
  },
  {
    "timestamp": "2025-08-30T09:38:06.278Z"
  },
  {
    "timestamp": "2025-08-30T09:52:18.812Z"
  },
  {
    "timestamp": "2025-08-30T10:19:50.752Z"
  },
  {
    "timestamp": "2025-08-30T10:40:27.503Z"
  },
  {
    "timestamp": "2025-08-30T10:52:21.164Z"
  },
  {
    "timestamp": "2025-08-30T11:16:12.851Z"
  },
  {
    "timestamp": "2025-08-30T11:38:25.121Z"
  },
  {
    "timestamp": "2025-08-30T11:52:13.484Z"
  },
  {
    "timestamp": "2025-08-30T12:40:04.044Z"
  },
  {
    "timestamp": "2025-08-30T13:04:58.001Z"
  },
  {
    "timestamp": "2025-08-30T13:31:44.925Z"
  },
  {
    "timestamp": "2025-08-30T13:52:21.819Z"
  },
  {
    "timestamp": "2025-08-30T14:17:40.269Z"
  },
  {
    "timestamp": "2025-08-30T14:38:52.724Z"
  },
  {
    "timestamp": "2025-08-30T14:52:17.870Z"
  },
  {
    "timestamp": "2025-08-30T15:19:24.494Z"
  },
  {
    "timestamp": "2025-08-30T15:38:07.782Z"
  },
  {
    "timestamp": "2025-08-30T15:52:16.981Z"
  },
  {
    "timestamp": "2025-08-30T16:24:22.076Z"
  },
  {
    "timestamp": "2025-08-30T16:43:13.808Z"
  },
  {
    "timestamp": "2025-08-30T16:54:44.346Z"
  },
  {
    "timestamp": "2025-08-30T17:16:36.337Z"
  },
  {
    "timestamp": "2025-08-30T17:38:12.707Z"
  },
  {
    "timestamp": "2025-08-30T17:52:16.878Z"
  },
  {
    "timestamp": "2025-08-30T18:27:51.978Z"
  },
  {
    "timestamp": "2025-08-30T18:46:05.861Z"
  },
  {
    "timestamp": "2025-08-30T19:15:32.752Z"
  },
  {
    "timestamp": "2025-08-30T19:38:06.190Z"
  },
  {
    "timestamp": "2025-08-30T19:51:54.905Z"
  },
  {
    "timestamp": "2025-08-30T20:21:35.894Z"
  },
  {
    "timestamp": "2025-08-30T20:39:49.184Z"
  },
  {
    "timestamp": "2025-08-30T20:52:00.335Z"
  },
  {
    "timestamp": "2025-08-30T21:18:16.921Z"
  },
  {
    "timestamp": "2025-08-30T21:38:14.516Z"
  },
  {
    "timestamp": "2025-08-30T21:52:15.918Z"
  },
  {
    "timestamp": "2025-08-30T22:18:48.674Z"
  },
  {
    "timestamp": "2025-08-30T22:40:05.676Z"
  },
  {
    "timestamp": "2025-08-30T22:52:09.987Z"
  },
  {
    "timestamp": "2025-08-30T23:19:02.947Z"
  },
  {
    "timestamp": "2025-08-30T23:38:42.293Z"
  },
  {
    "timestamp": "2025-08-30T23:52:21.854Z"
  },
  {
    "timestamp": "2025-08-31T01:50:03.560Z"
  },
  {
    "timestamp": "2025-08-31T03:08:34.423Z"
  },
  {
    "timestamp": "2025-08-31T03:44:48.349Z"
  }
]